LICENSE
MANIFEST.in
README.md
setup.py
sregistry/README.md
sregistry/__init__.py
sregistry/defaults.py
sregistry/version.py
sregistry.egg-info/PKG-INFO
sregistry.egg-info/SOURCES.txt
sregistry.egg-info/dependency_links.txt
sregistry.egg-info/entry_points.txt
sregistry.egg-info/not-zip-safe
sregistry.egg-info/requires.txt
sregistry.egg-info/top_level.txt
sregistry/auth/__init__.py
sregistry/auth/secrets.py
sregistry/auth/utils.py
sregistry/client/__init__.py
sregistry/client/add.py
sregistry/client/backend.py
sregistry/client/build.py
sregistry/client/delete.py
sregistry/client/get.py
sregistry/client/images.py
sregistry/client/inspect.py
sregistry/client/labels.py
sregistry/client/list.py
sregistry/client/mv.py
sregistry/client/pull.py
sregistry/client/push.py
sregistry/client/rename.py
sregistry/client/rm.py
sregistry/client/search.py
sregistry/client/share.py
sregistry/client/shell.py
sregistry/database/__init__.py
sregistry/database/dummy.py
sregistry/database/models.py
sregistry/database/robot.png
sregistry/database/sqlite.py
sregistry/logger/__init__.py
sregistry/logger/message.py
sregistry/logger/namer.py
sregistry/logger/progress.py
sregistry/logger/spinner.py
sregistry/main/README.md
sregistry/main/__init__.py
sregistry/main/__template__/__init__.py
sregistry/main/__template__/pull.py
sregistry/main/__template__/push.py
sregistry/main/__template__/query.py
sregistry/main/aws/__init__.py
sregistry/main/aws/api.py
sregistry/main/aws/pull.py
sregistry/main/base/__init__.py
sregistry/main/base/auth.py
sregistry/main/base/headers.py
sregistry/main/base/http.py
sregistry/main/base/inspect.py
sregistry/main/base/settings.py
sregistry/main/docker/__init__.py
sregistry/main/docker/api.py
sregistry/main/docker/blob2oci
sregistry/main/docker/environment.tar
sregistry/main/docker/pull.py
sregistry/main/docker/utils.py
sregistry/main/dropbox/__init__.py
sregistry/main/dropbox/pull.py
sregistry/main/dropbox/push.py
sregistry/main/dropbox/query.py
sregistry/main/dropbox/share.py
sregistry/main/gitlab/__init__.py
sregistry/main/gitlab/pull.py
sregistry/main/gitlab/query.py
sregistry/main/globus/__init__.py
sregistry/main/globus/pull.py
sregistry/main/globus/push.py
sregistry/main/globus/query.py
