Metadata-Version: 2.1
Name: sregistry
Version: 0.2.37
Summary: Command line tool for working with container storage
Home-page: http://www.github.com/singularityhub/sregistry-cli
Author: Vanessa Sochat
Author-email: vsochat@stanford.edu
Maintainer: Vanessa Sochat
Maintainer-email: vsochat@stanford.edu
License: LICENSE
Keywords: singularity containers registry hub
Platform: UNKNOWN
Classifier: Intended Audience :: Science/Research
Classifier: Intended Audience :: Developers
Classifier: License :: OSI Approved :: Mozilla Public License 2.0 (MPL 2.0)
Classifier: Programming Language :: C
Classifier: Programming Language :: Python
Classifier: Topic :: Software Development
Classifier: Topic :: Scientific/Engineering
Classifier: Operating System :: Unix
Classifier: Programming Language :: Python :: 3.3
Provides-Extra: all-basic
Provides-Extra: aws-basic
Provides-Extra: dropbox-basic
Provides-Extra: google-compute-basic
Provides-Extra: google-storage-basic
Provides-Extra: google-drive-basic
Provides-Extra: google-build-basic
Provides-Extra: globus-basic
Provides-Extra: registry-basic
Provides-Extra: s3-basic
Provides-Extra: swift-basic
Provides-Extra: all
Provides-Extra: aws
Provides-Extra: dropbox
Provides-Extra: google-compute
Provides-Extra: google-storage
Provides-Extra: google-drive
Provides-Extra: google-build
Provides-Extra: globus
Provides-Extra: registry
Provides-Extra: s3
Provides-Extra: swift
License-File: LICENSE
